setup.py
raulo_distributions/Binomialdistribution.py
raulo_distributions/Gaussiandistribution.py
raulo_distributions/Generaldistribution.py
raulo_distributions/__init__.py
raulo_distributions.egg-info/PKG-INFO
raulo_distributions.egg-info/SOURCES.txt
raulo_distributions.egg-info/dependency_links.txt
raulo_distributions.egg-info/not-zip-safe
raulo_distributions.egg-info/top_level.txt