Metadata-Version: 2.1
Name: raulo-distributions
Version: 0.1
Summary: Gaussian and Binomial distributions
Home-page: UNKNOWN
Author: Raul Serrano Mena
License: UNKNOWN
Platform: UNKNOWN
